easy_stat/__init__.py
easy_stat-1.0.2.dist-info/LICENSE
easy_stat-1.0.2.dist-info/METADATA
easy_stat-1.0.2.dist-info/WHEEL
easy_stat-1.0.2.dist-info/top_level.txt
easy_stat-1.0.2.dist-info/RECORD
