Metadata-Version: 2.1
Name: easy-stat
Version: 1.0.2
Summary: It's easy statistics
Author: s0urce
Author-email: boyarkin.gleb@gmail.com
Classifier: Programming Language :: Python :: 3
Classifier: License :: OSI Approved :: MIT License
Classifier: Operating System :: OS Independent
License-File: LICENSE
Requires-Dist: matplotlib
